plenario_api/__init__.py
plenario_api/admin.py
plenario_api/apps.py
plenario_api/models.py
plenario_api/settings.py
plenario_api/signals.py
plenario_api/urls.py
plenario_api/views.py
plenario_api/migrations/0001_initial.py
plenario_api/migrations/__init__.py
plenario_api-0.0.1.dist-info/DESCRIPTION.rst
plenario_api-0.0.1.dist-info/METADATA
plenario_api-0.0.1.dist-info/RECORD
plenario_api-0.0.1.dist-info/WHEEL
plenario_api-0.0.1.dist-info/metadata.json
plenario_api-0.0.1.dist-info/top_level.txt
tests/tests/__init__.py
tests/tests/bases.py
tests/tests/test_integrations.py
